{
  "RocoDataRows": {
    "200201": {
      "id": 200201,
      "pc_text": "动作系统banner",
      "mobile_text": "地图传送点banner"
    },
    "200604": {
      "id": 200604,
      "pc_text": "剧情-精元道具",
      "mobile_text": "家园-家具摆放-拖动家具"
    },
    "300101": {
      "id": 300101,
      "pc_text": "家园-家具摆放-放置剩余精灵窝",
      "mobile_text": "家园-精灵喂养-装备食物"
    },
    "500202": {
      "id": 500202,
      "pc_text": "7",
      "mobile_text": "8"
    },
    "500207": {
      "id": 500207,
      "pc_text": "9",
      "mobile_text": "10"
    },
    "500303": {
      "id": 500303,
      "pc_text": "11",
      "mobile_text": "12"
    }
  }
}