{
    "Name": "MEGAMAP_CONF",
    "Type": "EStruct",
    "UniqueKey": "id",
    "Properties": [
        {
            "Name": "id",
            "Type": "EUint32",
            "Offset": 0,
            "Size": 4
        },
        {
            "Name": "genre",
            "Type": "EString",
            "Offset": 4,
            "Size": 4,
            "CompressedSize": 4
        },
        {
            "Name": "class",
            "Type": "EInt32",
            "Offset": 8,
            "Size": 4
        },
        {
            "Name": "display_level_min",
            "Type": "EString",
            "Offset": 12,
            "Size": 4,
            "CompressedSize": 4
        },
        {
            "Name": "display_level_max",
            "Type": "EString",
            "Offset": 16,
            "Size": 4,
            "CompressedSize": 4
        },
        {
            "Name": "icon",
            "Type": "EString",
            "Offset": 20,
            "Size": 4,
            "CompressedSize": 4
        }
    ]
}